LICENSE
MANIFEST.in
README.rst
setup.cfg
setup.py
django_flex_user/__init__.py
django_flex_user/admin.py
django_flex_user/apps.py
django_flex_user/backends.py
django_flex_user/fields.py
django_flex_user/forms.py
django_flex_user/serializers.py
django_flex_user/urls.py
django_flex_user/util.py
django_flex_user/validators.py
django_flex_user/verification.py
django_flex_user/views.py
django_flex_user.egg-info/PKG-INFO
django_flex_user.egg-info/SOURCES.txt
django_flex_user.egg-info/dependency_links.txt
django_flex_user.egg-info/requires.txt
django_flex_user.egg-info/top_level.txt
django_flex_user/migrations/0001_initial.py
django_flex_user/migrations/0002_emailtoken_phonetoken.py
django_flex_user/migrations/__init__.py
django_flex_user/models/__init__.py
django_flex_user/models/otp.py
django_flex_user/models/user.py
django_flex_user/templates/django_flex_user/.gitkeep